README.md
setup.cfg
setup.py
chainable/__init__.py
chainable/chainable.py
chainable/cli.py
chainable.egg-info/PKG-INFO
chainable.egg-info/SOURCES.txt
chainable.egg-info/dependency_links.txt
chainable.egg-info/entry_points.txt
chainable.egg-info/top_level.txt
chainable/tests/__init__.py
chainable/tests/conftest.py
tests/__init__.py
tests/test_chainable.py