Metadata-Version: 1.1
Name: chainable
Version: 0.1.6
Summary: Method chaining built on generators
Home-page: https://github.com/olirice/chainable
Author: Oliver Rice
Author-email: oliver@oliverrice.com
License: MIT
Platform: UNKNOWN
Classifier: Development Status :: 4 - Beta
Classifier: Natural Language :: English
Classifier: Operating System :: OS Independent
Classifier: Programming Language :: Python
Classifier: Programming Language :: Python :: 3
Classifier: Programming Language :: Python :: 3.5
Classifier: Programming Language :: Python :: 3.6
